strands_fun_tools/__init__.py
strands_fun_tools/__version__.py
strands_fun_tools/asciimatics_ui.py
strands_fun_tools/bluetooth.py
strands_fun_tools/chess.py
strands_fun_tools/clipboard.py
strands_fun_tools/cursor.py
strands_fun_tools/dialog.py
strands_fun_tools/dynamic_package.py
strands_fun_tools/face_recognition.py
strands_fun_tools/human_typer.py
strands_fun_tools/listen.py
strands_fun_tools/npm.py
strands_fun_tools/screen_reader.py
strands_fun_tools/spinner_generator.py
strands_fun_tools/take_photo.py
strands_fun_tools/template.py
strands_fun_tools/utility.py
strands_fun_tools/yolo_vision.py
strands_fun_tools-0.3.0.dist-info/licenses/LICENSE
strands_fun_tools-0.3.0.dist-info/METADATA
strands_fun_tools-0.3.0.dist-info/WHEEL
strands_fun_tools-0.3.0.dist-info/top_level.txt
strands_fun_tools-0.3.0.dist-info/RECORD
