Metadata-Version: 2.4
Name: strands-fun-tools
Version: 0.3.0
Summary: Creative and utility tools for Strands AI agents - interactive experiences
Home-page: https://github.com/cagataycali/strands-fun-tools
Author: Cagatay Cali
Author-email: Cagatay Cali <cagataycali@icloud.com>
License: Apache-2.0
Project-URL: Homepage, https://github.com/cagataycali/strands-fun-tools
Project-URL: Documentation, https://github.com/cagataycali/strands-fun-tools
Project-URL: Repository, https://github.com/cagataycali/strands-fun-tools
Project-URL: Bug Tracker, https://github.com/cagataycali/strands-fun-tools/issues
Keywords: strands,ai,agents,tools,bluetooth,chess,clipboard,cursor,vision,audio,fun,creative
Classifier: Development Status :: 3 - Alpha
Classifier: Intended Audience :: Developers
Classifier: License :: OSI Approved :: Apache Software License
Classifier: Programming Language :: Python :: 3
Classifier: Programming Language :: Python :: 3.10
Classifier: Programming Language :: Python :: 3.11
Classifier: Programming Language :: Python :: 3.12
Classifier: Programming Language :: Python :: 3.13
Classifier: Programming Language :: Python :: 3.14
Classifier: Topic :: Software Development :: Libraries :: Python Modules
Classifier: Topic :: Scientific/Engineering :: Artificial Intelligence
Classifier: Topic :: Multimedia
Classifier: Topic :: Games/Entertainment
Requires-Python: >=3.10
License-File: LICENSE
Requires-Dist: strands-agents
Provides-Extra: all
Requires-Dist: pyautogui; extra == "all"
Requires-Dist: pyperclip; extra == "all"
Requires-Dist: pillow; extra == "all"
Requires-Dist: stockfish; extra == "all"
Requires-Dist: rich; extra == "all"
Requires-Dist: opencv-python; extra == "all"
Requires-Dist: boto3; extra == "all"
Requires-Dist: halo; extra == "all"
Requires-Dist: colorama; extra == "all"
Requires-Dist: jinja2; extra == "all"
Requires-Dist: pyyaml; extra == "all"
Requires-Dist: cryptography; extra == "all"
Requires-Dist: pytesseract; extra == "all"
Requires-Dist: bleak; extra == "all"
Requires-Dist: prompt_toolkit; extra == "all"
Requires-Dist: asciimatics; extra == "all"
Provides-Extra: cursor
Requires-Dist: pyautogui; extra == "cursor"
Provides-Extra: clipboard
Requires-Dist: pyperclip; extra == "clipboard"
Provides-Extra: chess
Requires-Dist: stockfish; extra == "chess"
Requires-Dist: rich; extra == "chess"
Provides-Extra: vision
Requires-Dist: opencv-python; extra == "vision"
Requires-Dist: ultralytics; extra == "vision"
Requires-Dist: pytesseract; extra == "vision"
Requires-Dist: pillow; extra == "vision"
Provides-Extra: bluetooth
Requires-Dist: bleak; extra == "bluetooth"
Provides-Extra: audio
Requires-Dist: openai-whisper; extra == "audio"
Requires-Dist: sounddevice; extra == "audio"
Requires-Dist: webrtcvad; extra == "audio"
Provides-Extra: display
Requires-Dist: rich; extra == "display"
Requires-Dist: halo; extra == "display"
Requires-Dist: colorama; extra == "display"
Provides-Extra: template
Requires-Dist: jinja2; extra == "template"
Requires-Dist: rich; extra == "template"
Provides-Extra: utility
Requires-Dist: pyyaml; extra == "utility"
Requires-Dist: cryptography; extra == "utility"
Provides-Extra: face
Requires-Dist: opencv-python; extra == "face"
Requires-Dist: boto3; extra == "face"
Provides-Extra: dialog
Requires-Dist: prompt_toolkit; extra == "dialog"
Provides-Extra: ui
Requires-Dist: asciimatics; extra == "ui"
Provides-Extra: dev
Requires-Dist: mypy>=1.8.0; extra == "dev"
Requires-Dist: black>=24.0.0; extra == "dev"
Requires-Dist: pytest>=7.4.0; extra == "dev"
Requires-Dist: pytest-asyncio>=0.21.0; extra == "dev"
Requires-Dist: ruff>=0.1.0; extra == "dev"
Dynamic: author
Dynamic: home-page
Dynamic: license-file
Dynamic: requires-python
